desfire/DESFire.py
desfire/__init__.py
desfire/cmac.py
desfire/devices/__init__.py
desfire/devices/base.py
desfire/devices/pcsc.py
desfire/devices/pn532.py
desfire/diversify.py
desfire/enums/__init__.py
desfire/enums/desfire_command.py
desfire/enums/desfire_communication_mode.py
desfire/enums/desfire_filetype.py
desfire/enums/desfire_keysettings.py
desfire/enums/desfire_keytype.py
desfire/enums/desfire_status.py
desfire/exceptions.py
desfire/key.py
desfire/schemas/__init__.py
desfire/schemas/card_version.py
desfire/schemas/file_permissions.py
desfire/schemas/file_settings.py
desfire/schemas/key_settings.py
desfire/util.py
python_desfire-0.1.5.dist-info/LICENSE
python_desfire-0.1.5.dist-info/METADATA
python_desfire-0.1.5.dist-info/WHEEL
python_desfire-0.1.5.dist-info/RECORD
