Metadata-Version: 2.3
Name: python-desfire
Version: 0.1.5
Summary: DESFire library for python
License: MIT
Author: Daniel Herrmann
Author-email: daniel.herrmann@makerspace-darmstadt.de
Requires-Python: >=3.11
Classifier: License :: OSI Approved :: MIT License
Classifier: Programming Language :: Python :: 3
Classifier: Programming Language :: Python :: 3.11
Classifier: Programming Language :: Python :: 3.12
Classifier: Programming Language :: Python :: 3.13
Provides-Extra: all
Provides-Extra: pcsc
Provides-Extra: pn532
Requires-Dist: pycryptodome (>=3.21.0,<4.0.0)
Requires-Dist: pyscard (>=2.2.1,<3.0.0) ; extra == "all"
Requires-Dist: pyscard (>=2.2.1,<3.0.0) ; extra == "pcsc"
Requires-Dist: pyserial (>=3.5,<4.0) ; extra == "all"
Requires-Dist: pyserial (>=3.5,<4.0) ; extra == "pn532"
